hatch_build.py
dask-gateway-proxy/.gitignore
dask-gateway-proxy/README.md
dask-gateway-proxy/go.mod
dask-gateway-proxy/go.sum
dask-gateway-proxy/cmd/dask-gateway-proxy/main.go
dask-gateway-proxy/internal/logging/logging.go
dask-gateway-proxy/pkg/router/router.go
dask-gateway-proxy/pkg/router/router_test.go
dask-gateway-proxy/pkg/sni/sni.go
dask_gateway_server/__init__.py
dask_gateway_server/__main__.py
dask_gateway_server/_version.py
dask_gateway_server/app.py
dask_gateway_server/auth.py
dask_gateway_server/models.py
dask_gateway_server/options.py
dask_gateway_server/routes.py
dask_gateway_server/tls.py
dask_gateway_server/traitlets.py
dask_gateway_server/utils.py
dask_gateway_server/workqueue.py
dask_gateway_server/backends/__init__.py
dask_gateway_server/backends/base.py
dask_gateway_server/backends/db_base.py
dask_gateway_server/backends/inprocess.py
dask_gateway_server/backends/local.py
dask_gateway_server/backends/yarn.py
dask_gateway_server/backends/jobqueue/__init__.py
dask_gateway_server/backends/jobqueue/base.py
dask_gateway_server/backends/jobqueue/launcher.py
dask_gateway_server/backends/jobqueue/pbs.py
dask_gateway_server/backends/jobqueue/slurm.py
dask_gateway_server/backends/kubernetes/__init__.py
dask_gateway_server/backends/kubernetes/backend.py
dask_gateway_server/backends/kubernetes/controller.py
dask_gateway_server/backends/kubernetes/utils.py
dask_gateway_server/proxy/__init__.py
dask_gateway_server/proxy/core.py
dask_gateway_server/proxy/dask-gateway-proxy
dask_gateway_server-2025.4.0.dist-info/METADATA
dask_gateway_server-2025.4.0.dist-info/WHEEL
dask_gateway_server-2025.4.0.dist-info/entry_points.txt
dask_gateway_server-2025.4.0.dist-info/licenses/LICENSE
dask_gateway_server-2025.4.0.dist-info/RECORD
