Metadata-Version: 2.4
Name: dask-gateway-server
Version: 2025.4.0
Summary: A multi-tenant server for securely deploying and managing multiple Dask clusters.
Project-URL: Documentation, https://gateway.dask.org/
Project-URL: Source, https://github.com/dask/dask-gateway/
Project-URL: Issues, https://github.com/dask/dask-gateway/issues
Author-email: Jim Crist-Harif <jcristharif@gmail.com>
License: Copyright (c) 2019, Jim Crist-Harif
License-File: LICENSE
Keywords: HPC,cluster,dask,distributed,hadoop,kubernetes
Classifier: Development Status :: 5 - Production/Stable
Classifier: Intended Audience :: Developers
Classifier: Intended Audience :: Science/Research
Classifier: Intended Audience :: System Administrators
Classifier: License :: OSI Approved :: BSD License
Classifier: Programming Language :: Python :: 3
Classifier: Topic :: Scientific/Engineering
Classifier: Topic :: System :: Distributed Computing
Classifier: Topic :: System :: Systems Administration
Requires-Python: >=3.10
Requires-Dist: aiohttp>=3.9.0
Requires-Dist: async-timeout; python_version < '3.11'
Requires-Dist: colorlog
Requires-Dist: cryptography
Requires-Dist: traitlets>=5.2.2.post1
Provides-Extra: all-backends
Requires-Dist: kubernetes-asyncio; extra == 'all-backends'
Requires-Dist: protobuf<3.21; extra == 'all-backends'
Requires-Dist: skein>=0.7.3; extra == 'all-backends'
Requires-Dist: sqlalchemy>=2.0.0; extra == 'all-backends'
Provides-Extra: jobqueue
Requires-Dist: sqlalchemy>=2.0.0; extra == 'jobqueue'
Provides-Extra: kerberos
Requires-Dist: pykerberos; extra == 'kerberos'
Provides-Extra: kubernetes
Requires-Dist: kubernetes-asyncio; extra == 'kubernetes'
Provides-Extra: local
Requires-Dist: sqlalchemy>=2.0.0; extra == 'local'
Provides-Extra: yarn
Requires-Dist: protobuf<3.21; extra == 'yarn'
Requires-Dist: skein>=0.7.3; extra == 'yarn'
Requires-Dist: sqlalchemy>=2.0.0; extra == 'yarn'
